picpurify/__init__.py
picpurify/api.py
picpurify/cli.py
picpurify/version.py
picpurify-1.0.3.dist-info/LICENSE
picpurify-1.0.3.dist-info/METADATA
picpurify-1.0.3.dist-info/WHEEL
picpurify-1.0.3.dist-info/top_level.txt
picpurify-1.0.3.dist-info/RECORD
