Metadata-Version: 2.1
Name: picpurify
Version: 1.0.3
Summary: Python client library for accessing PicPurify moderation API
Home-page: https://www.picpurify.com
Author: Romain Cousseau
Author-email: romain.cousseau@picpurify.com
License: MIT license
Platform: UNKNOWN
Requires-Python: >=2.7
Requires-Dist: requests (>=2.13.0)
